mikrotik_certbot/__init__.py
mikrotik_certbot/__main__.py
mikrotik_certbot/certificates.py
mikrotik_certbot/config.py
mikrotik_certbot/routeros.py
mikrotik_certbot/workflow.py
mikrotik_certbot-1.0.0.dist-info/METADATA
mikrotik_certbot-1.0.0.dist-info/WHEEL
mikrotik_certbot-1.0.0.dist-info/entry_points.txt
mikrotik_certbot-1.0.0.dist-info/licenses/LICENSE
mikrotik_certbot-1.0.0.dist-info/RECORD
