Metadata-Version: 2.4
Name: mikrotik-certbot
Version: 1.0.0
Summary: Certbot deploy hook script to upload renewed Let's Encrypt certificates to a MikroTik RouterOS device via the REST API.
Project-URL: Homepage, https://github.com/karrots/mikrotik-certbot
Project-URL: Repository, https://github.com/karrots/mikrotik-certbot
Project-URL: Issues, https://github.com/karrots/mikrotik-certbot/issues
Author-email: Jonathan Karras <6307688+karrots@users.noreply.github.com>
License: MIT License
License-File: LICENSE
Keywords: automation,certbot,certificate,letsencrypt,mikrotik,routeros
Classifier: Intended Audience :: System Administrators
Classifier: License :: OSI Approved :: MIT License
Classifier: Operating System :: OS Independent
Classifier: Programming Language :: Python :: 3
Classifier: Topic :: Internet :: Name Service (DNS)
Classifier: Topic :: Security :: Cryptography
Requires-Python: >=3.11
Requires-Dist: cryptography>=41.0.0
Requires-Dist: paramiko>=3.4.0
Requires-Dist: requests>=2.32.0
